{
  "project_info": {
    "project_number": "1015201759818",
    "project_id": "project2026adeyemi",
    "storage_bucket": "project2026adeyemi.firebasestorage.app"
  },
  "client": [
    {
      "client_info": {
        "mobilesdk_app_id": "1:1015201759818:android:e65a4ea11ffc9a80b65cb3",
        "android_client_info": {
          "package_name": "com.example.furniture"
        }
      },
      "oauth_client": [],
      "api_key": [
        {
          "current_key": "AIzaSyBiRdxPNXhYLv2hYxZpxp1rzLsFQhw4QTo"
        }
      ],
      "services": {
        "appinvite_service": {
          "other_platform_oauth_client": []
        }
      }
    }
  ],
  "configuration_version": "1"
}